efficient_context/__init__.py
efficient_context/context_manager.py
efficient_context/chunking/__init__.py
efficient_context/chunking/base.py
efficient_context/chunking/semantic_chunker.py
efficient_context/compression/__init__.py
efficient_context/compression/base.py
efficient_context/compression/semantic_deduplicator.py
efficient_context/memory/__init__.py
efficient_context/memory/memory_manager.py
efficient_context/retrieval/__init__.py
efficient_context/retrieval/base.py
efficient_context/retrieval/cpu_optimized_retriever.py
efficient_context/utils/__init__.py
efficient_context/utils/text.py
efficient_context-0.1.0.dist-info/licenses/LICENSE
efficient_context-0.1.0.dist-info/METADATA
efficient_context-0.1.0.dist-info/WHEEL
efficient_context-0.1.0.dist-info/top_level.txt
efficient_context-0.1.0.dist-info/RECORD
