Metadata-Version: 2.4
Name: efficient-context
Version: 0.1.0
Summary: Optimize LLM context handling in CPU-constrained environments
Home-page: https://github.com/biswanathroul/efficient-context
Author: Biswanath Roul
Keywords: llm,context,optimization,cpu,memory,efficiency,nlp
Classifier: Programming Language :: Python :: 3
Classifier: License :: OSI Approved :: MIT License
Classifier: Operating System :: OS Independent
Classifier: Topic :: Scientific/Engineering :: Artificial Intelligence
Requires-Python: >=3.7
License-File: LICENSE
Requires-Dist: numpy>=1.19.0
Requires-Dist: scikit-learn>=0.24.0
Requires-Dist: sentence-transformers>=2.2.2
Requires-Dist: nltk>=3.6.0
Requires-Dist: pydantic>=1.8.0
Requires-Dist: tqdm>=4.62.0
Dynamic: author
Dynamic: classifier
Dynamic: description
Dynamic: description-content-type
Dynamic: home-page
Dynamic: keywords
Dynamic: license-file
Dynamic: requires-dist
Dynamic: requires-python
Dynamic: summary
